{
    "-2140192274": "",
    "-2135121567": "PATHSET_CHARACTER_HONOR",
    "-2134496041": "PATHSET_COUPONS",
    "-2131349385": "",
    "-2111754046": "",
    "-2091611647": "PATHSET_WARDROBE_HAIR",
    "-2085256260": "PATHSET_XP",
    "-2080958556": "",
    "-2046660348": "PATHSET_MOONSHINER_CRAFT_OUTPUT",
    "-2026128014": "PATHSET_WEAPON_BOW",
    "-1993705630": "PATHSET_WARDROBE_LEFT_RINGS",
    "-1983405085": "",
    "-1936787920": "PATHSET_WARDROBE_GAUNTLETS",
    "-1925887917": "PATHSET_WEAPON_RIFLE",
    "-1886878468": "PATHSET_WARDROBE_MOLES",
    "-1884340503": "PATHSET_KIT",
    "-1849915820": "",
    "-1762468255": "PATHSET_PLAYER_CURRENCY",
    "-1749627771": "PATHSET_WARDROBE_BLUSH",
    "-1737896753": "PATHSET_FISHINGROD",
    "-1694766828": "PATHSET_WARDROBE_SKIN_MOTTLING",
    "-1665520196": "PATHSET_COACH",
    "-1528805350": "PATHSET_WARDROBE_SATCHEL",
    "-1513277909": "PATHSET_WARDROBE_TEETH",
    "-1506116499": "PATHSET_WARDROBE_WAIST_STRAP",
    "-1459392356": "PATHSET_EMOTE_TAUNTS",
    "-1421768793": "PATHSET_MATERIALS",
    "-1399807798": "PATHSET_MOONSHINER_CRAFT_INPUT",
    "-1366313573": "PATHSET_EMOTE_ACTIONS",
    "-1359763504": "",
    "-1312499551": "PATHSET_WARDROBE_HEAD",
    "-1158643834": "PATHSET_WARDROBE_EYES",
    "-1149444392": "PATHSET_WARDROBE_AGEING",
    "-1120445111": "",
    "-1117338237": "PATHSET_WEAPON_KNIFE",
    "-1103826698": "PATHSET_WARDROBE_RIGHT_RINGS",
    "-1093083449": "PATHSET_WARDROBE_NECKWEAR_1",
    "-1075092815": "",
    "-1073442724": "",
    "-1068276995": "",
    "-1039040699": "PATHSET_PURCHASED_CONTENT",
    "-1024000304": "PATHSET_MOONSHINER_UPGRADE",
    "-975036572": "",
    "-963679103": "PATHSET_CAMP_TENT",
    "-858117838": "PATHSET_WARDROBE_FOUNDATION",
    "-797691890": "PATHSET_VOUCHERS",
    "-791662549": "PATHSET_DEFAULT_STABLE",
    "-755339956": "PATHSET_VALUABLES",
    "-753081570": "PATHSET_PROVISIONS",
    "-721926777": "PATHSET_WARDROBE_EYEWEAR",
    "-678935619": "PATHSET_ROLE_ITEMS",
    "-640708660": "PATHSET_WARDROBE_LOADOUT_1",
    "-626946447": "PATHSET_EMOTE_TWIRL_GUN",
    "-557799831": "",
    "-544139983": "PATHSET_WARDROBE_LOWER_GARB",
    "-525392477": "",
    "-448669403": "PATHSET_WARDROBE_GLOVES",
    "-383965953": "PATHSET_HORSE",
    "-352669150": "PATHSET_WARDROBE_LOADOUT_2",
    "-299534372": "PATHSET_WARDROBE_BEARD",
    "-261706549": "PATHSET_WARDROBE_EYELINER",
    "-240974146": "PATHSET_MOONSHINER_BAR_PHOTO",
    "-216365117": "PATHSET_INGREDIENTS",
    "-197475497": "PATHSET_WEAPON_UNIQUE",
    "-190710557": "",
    "-187741064": "",
    "-181990688": "",
    "-179988445": "PATHSET_WEAPON_THROWN",
    "-114417377": "PATHSET_CAMP_EQUIPMENT",
    "-62982151": "PATHSET_CAMP_FLAG",
    "-56382763": "PATHSET_WARDROBE_PLAYER_BODY_TYPE",
    "35266688": "PATHSET_EMOTE_REACTIONS",
    "35889520": "",
    "62055322": "PATHSET_WARDROBE_LOADOUT_4",
    "260053584": "PATHSET_MISSION_TIMERS",
    "308851732": "",
    "344624110": "",
    "354026760": "PATHSET_WARDROBE_OUTFITS",
    "406210431": "",
    "421102067": "PATHSET_CAMP_FOLLOWER_OUTFIT",
    "459004547": "PATHSET_WARDROBE_SPOTS",
    "460282787": "PATHSET_WARDROBE",
    "470198362": "PATHSET_NATURALIST_COMPENDIUM",
    "544617345": "PATHSET_EMOTE_GREETS",
    "641019715": "",
    "661743427": "PATHSET_WARDROBE_UPPER_GARB",
    "738920829": "PATHSET_WARDROBE_LIPSTICK",
    "827172787": "PATHSET_WARDROBE_UPPER_BODY",
    "831782332": "PATHSET_UPGRADE",
    "835600328": "PATHSET_WARDROBE_LOADOUT_3",
    "860889056": "PATHSET_CAMP_DOG",
    "885107933": "PATHSET_WARDROBE_PLAYER_GENDER",
    "939587529": "PATHSET_CAMP_THEME",
    "943374466": "PATHSET_CAMP_MUSIC",
    "953929187": "PATHSET_WARDROBE_LOADOUT_8",
    "1003615152": "",
    "1068942980": "",
    "1186578101": "PATHSET_WARDROBE_PLAYER_VOICE",
    "1190921426": "PATHSET_WARDROBE_LOWER_BODY",
    "1225938571": "",
    "1235710344": "PATHSET_WATCHES",
    "1264316425": "PATHSET_WARDROBE_FRECKLES",
    "1269822347": "PATHSET_WARDROBE_LOADOUT_9",
    "1274587267": "PATHSET_CHARACTER_PROGRESSION",
    "1295324714": "PATHSET_WARDROBE_EYEBROWS",
    "1305590950": "PATHSET_MOONSHINER_THEME",
    "1376211977": "PATHSET_MOONSHINER_LOCATION",
    "1424014991": "PATHSET_CHARACTER_NOTORIETY",
    "1588910662": "PATHSET_WARDROBE_COMPLEXION",
    "1659380590": "PATHSET_WEAPON_PISTOL",
    "1714964326": "PATHSET_CONSUMABLES",
    "1878992887": "",
    "1918670364": "PATHSET_WARDROBE_SCAR",
    "1934278166": "PATHSET_WEAPON_MELEE",
    "1997010504": "PATHSET_SATCHEL",
    "2023956366": "PATHSET_HERBS",
    "2101960676": "PATHSET_NATURALIST_COMPENDIUM_STAMP",
    "2138268270": "PATHSET_WARDROBE_EYESHADOW"
}